android_mirror/__init__.py
android_mirror/__main__.py
android_mirror/__version__.py
android_mirror/adb_handler.py
android_mirror/adb_utils.py
android_mirror/clear_data.py
android_mirror/dep_check.py
android_mirror/device_detector.py
android_mirror/bin/AdbWinApi.dll
android_mirror/bin/AdbWinUsbApi.dll
android_mirror/bin/SDL2.dll
android_mirror/bin/adb.exe
android_mirror/bin/avcodec-61.dll
android_mirror/bin/avformat-61.dll
android_mirror/bin/avutil-59.dll
android_mirror/bin/icon.png
android_mirror/bin/libusb-1.0.dll
android_mirror/bin/open_a_terminal_here.bat
android_mirror/bin/readme.docx
android_mirror/bin/readme.txt
android_mirror/bin/scrcpy-console.bat
android_mirror/bin/scrcpy-noconsole.vbs
android_mirror/bin/scrcpy-server
android_mirror/bin/scrcpy.exe
android_mirror/bin/swresample-5.dll
android_mirror-1.1.0.dist-info/LICENSE
android_mirror-1.1.0.dist-info/METADATA
android_mirror-1.1.0.dist-info/WHEEL
android_mirror-1.1.0.dist-info/entry_points.txt
android_mirror-1.1.0.dist-info/top_level.txt
android_mirror-1.1.0.dist-info/RECORD
