Metadata-Version: 2.1
Name: android_mirror
Version: 1.1.0
Summary: A fixed-version Android screen mirroring tool using bundled scrcpy
Home-page: https://github.com/kdiitg/android_mirror
Author: Kuldeep Singh
License: MIT
Project-URL: Documentation, https://github.com/kdiitg/android_mirror
Project-URL: Source, https://github.com/kdiitg/android_mirror
Project-URL: Bug Tracker, https://github.com/kdiitg/android_mirror/issues
Keywords: scrcpy android mirror screen cast cli adb
Classifier: Programming Language :: Python :: 3
Classifier: License :: OSI Approved :: MIT License
Classifier: Operating System :: Microsoft :: Windows
Classifier: Topic :: Utilities
Requires-Python: >=3.7
License-File: LICENSE
